{
  "cards": [
    {
      "id": "1774465456902-7030",
      "de": "der Zahnarzt",
      "en": "стоматолог",
      "article": "",
      "notes": "",
      "created_at": "2026-03-25T19:04:16.902177+00:00",
      "due_at": "2026-03-26T19:56:12.128828+00:00",
      "interval_days": 1,
      "ease": 2.4,
      "reps": 1,
      "lapses": 0
    },
    {
      "id": "1774465424781-8906",
      "de": "der Backenzahn",
      "en": "коренной зуб",
      "article": "",
      "notes": "",
      "created_at": "2026-03-25T19:03:44.781211+00:00",
      "due_at": "2026-03-26T19:56:05.224564+00:00",
      "interval_days": 1,
      "ease": 2.4,
      "reps": 1,
      "lapses": 0
    },
    {
      "id": "seed-0001",
      "de": "der Krach",
      "en": "шум, грохот",
      "article": "",
      "notes": "",
      "created_at": "2026-03-25T19:10:00+00:00",
      "due_at": "2026-03-26T19:56:19.406368+00:00",
      "interval_days": 1,
      "ease": 2.4,
      "reps": 1,
      "lapses": 0
    },
    {
      "id": "seed-0002",
      "de": "der Mensch",
      "en": "человек",
      "article": "",
      "notes": "",
      "created_at": "2026-03-25T19:10:00+00:00",
      "due_at": "2026-03-25T19:10:00+00:00",
      "interval_days": 0,
      "ease": 2.3,
      "reps": 0,
      "lapses": 0
    },
    {
      "id": "seed-0003",
      "de": "der Schatz",
      "en": "сокровище; (разг.) любимый",
      "article": "",
      "notes": "",
      "created_at": "2026-03-25T19:10:00+00:00",
      "due_at": "2026-03-25T19:10:00+00:00",
      "interval_days": 0,
      "ease": 2.3,
      "reps": 0,
      "lapses": 0
    },
    {
      "id": "seed-0004",
      "de": "die Ruhe",
      "en": "покой, тишина",
      "article": "",
      "notes": "",
      "created_at": "2026-03-25T19:10:00+00:00",
      "due_at": "2026-03-25T19:10:00+00:00",
      "interval_days": 0,
      "ease": 2.3,
      "reps": 0,
      "lapses": 0
    },
    {
      "id": "seed-0005",
      "de": "die Hose",
      "en": "брюки",
      "article": "",
      "notes": "",
      "created_at": "2026-03-25T19:10:00+00:00",
      "due_at": "2026-03-25T19:10:00+00:00",
      "interval_days": 0,
      "ease": 2.3,
      "reps": 0,
      "lapses": 0
    },
    {
      "id": "seed-0006",
      "de": "der Kühlschrank",
      "en": "холодильник",
      "article": "",
      "notes": "",
      "created_at": "2026-03-25T19:10:00+00:00",
      "due_at": "2026-03-25T19:10:00+00:00",
      "interval_days": 0,
      "ease": 2.3,
      "reps": 0,
      "lapses": 0
    },
    {
      "id": "seed-0007",
      "de": "die Nachbarn",
      "en": "соседи",
      "article": "",
      "notes": "",
      "created_at": "2026-03-25T19:10:00+00:00",
      "due_at": "2026-03-25T19:10:00+00:00",
      "interval_days": 0,
      "ease": 2.3,
      "reps": 0,
      "lapses": 0
    },
    {
      "id": "seed-0008",
      "de": "die Lösung",
      "en": "решение",
      "article": "",
      "notes": "",
      "created_at": "2026-03-25T19:10:00+00:00",
      "due_at": "2026-03-25T19:10:00+00:00",
      "interval_days": 0,
      "ease": 2.3,
      "reps": 0,
      "lapses": 0
    },
    {
      "id": "seed-0009",
      "de": "die Mitte",
      "en": "середина",
      "article": "",
      "notes": "",
      "created_at": "2026-03-25T19:10:00+00:00",
      "due_at": "2026-03-25T19:10:00+00:00",
      "interval_days": 0,
      "ease": 2.3,
      "reps": 0,
      "lapses": 0
    },
    {
      "id": "seed-0010",
      "de": "die Nebenkosten",
      "en": "коммунальные расходы",
      "article": "",
      "notes": "",
      "created_at": "2026-03-25T19:10:00+00:00",
      "due_at": "2026-03-25T19:10:00+00:00",
      "interval_days": 0,
      "ease": 2.3,
      "reps": 0,
      "lapses": 0
    },
    {
      "id": "seed-0011",
      "de": "die Innenstadt",
      "en": "центр города",
      "article": "",
      "notes": "",
      "created_at": "2026-03-25T19:10:00+00:00",
      "due_at": "2026-03-25T19:10:00+00:00",
      "interval_days": 0,
      "ease": 2.3,
      "reps": 0,
      "lapses": 0
    },
    {
      "id": "seed-0012",
      "de": "das Land",
      "en": "страна; земля",
      "article": "",
      "notes": "",
      "created_at": "2026-03-25T19:10:00+00:00",
      "due_at": "2026-03-25T19:10:00+00:00",
      "interval_days": 0,
      "ease": 2.3,
      "reps": 0,
      "lapses": 0
    },
    {
      "id": "seed-0013",
      "de": "der Wald",
      "en": "лес",
      "article": "",
      "notes": "",
      "created_at": "2026-03-25T19:10:00+00:00",
      "due_at": "2026-03-25T19:10:00+00:00",
      "interval_days": 0,
      "ease": 2.3,
      "reps": 0,
      "lapses": 0
    },
    {
      "id": "seed-0014",
      "de": "die Sachen",
      "en": "вещи",
      "article": "",
      "notes": "",
      "created_at": "2026-03-25T19:10:00+00:00",
      "due_at": "2026-03-25T19:10:00+00:00",
      "interval_days": 0,
      "ease": 2.3,
      "reps": 0,
      "lapses": 0
    },
    {
      "id": "seed-0015",
      "de": "der Himmel",
      "en": "небо",
      "article": "",
      "notes": "",
      "created_at": "2026-03-25T19:10:00+00:00",
      "due_at": "2026-03-25T19:10:00+00:00",
      "interval_days": 0,
      "ease": 2.3,
      "reps": 0,
      "lapses": 0
    },
    {
      "id": "seed-0016",
      "de": "die Angst",
      "en": "страх",
      "article": "",
      "notes": "",
      "created_at": "2026-03-25T19:10:00+00:00",
      "due_at": "2026-03-25T19:10:00+00:00",
      "interval_days": 0,
      "ease": 2.3,
      "reps": 0,
      "lapses": 0
    },
    {
      "id": "seed-0017",
      "de": "der Bauch",
      "en": "живот",
      "article": "",
      "notes": "",
      "created_at": "2026-03-25T19:10:00+00:00",
      "due_at": "2026-03-25T19:10:00+00:00",
      "interval_days": 0,
      "ease": 2.3,
      "reps": 0,
      "lapses": 0
    },
    {
      "id": "seed-0018",
      "de": "das Beispiel",
      "en": "пример",
      "article": "",
      "notes": "",
      "created_at": "2026-03-25T19:10:00+00:00",
      "due_at": "2026-03-25T19:10:00+00:00",
      "interval_days": 0,
      "ease": 2.3,
      "reps": 0,
      "lapses": 0
    },
    {
      "id": "seed-0019",
      "de": "die Lücke",
      "en": "пробел, пропуск",
      "article": "",
      "notes": "",
      "created_at": "2026-03-25T19:10:00+00:00",
      "due_at": "2026-03-25T19:10:00+00:00",
      "interval_days": 0,
      "ease": 2.3,
      "reps": 0,
      "lapses": 0
    },
    {
      "id": "seed-0020",
      "de": "die Rückseite",
      "en": "обратная сторона",
      "article": "",
      "notes": "",
      "created_at": "2026-03-25T19:10:00+00:00",
      "due_at": "2026-03-25T19:10:00+00:00",
      "interval_days": 0,
      "ease": 2.3,
      "reps": 0,
      "lapses": 0
    },
    {
      "id": "seed-0021",
      "de": "die Geduld",
      "en": "терпение",
      "article": "",
      "notes": "",
      "created_at": "2026-03-25T19:10:00+00:00",
      "due_at": "2026-03-25T19:10:00+00:00",
      "interval_days": 0,
      "ease": 2.3,
      "reps": 0,
      "lapses": 0
    },
    {
      "id": "seed-0022",
      "de": "der Baum",
      "en": "дерево",
      "article": "",
      "notes": "",
      "created_at": "2026-03-25T19:10:00+00:00",
      "due_at": "2026-03-25T19:10:00+00:00",
      "interval_days": 0,
      "ease": 2.3,
      "reps": 0,
      "lapses": 0
    },
    {
      "id": "seed-0023",
      "de": "der Fluss",
      "en": "река",
      "article": "",
      "notes": "",
      "created_at": "2026-03-25T19:10:00+00:00",
      "due_at": "2026-03-25T19:10:00+00:00",
      "interval_days": 0,
      "ease": 2.3,
      "reps": 0,
      "lapses": 0
    },
    {
      "id": "seed-0024",
      "de": "der Koffer",
      "en": "чемодан",
      "article": "",
      "notes": "",
      "created_at": "2026-03-25T19:10:00+00:00",
      "due_at": "2026-03-25T19:10:00+00:00",
      "interval_days": 0,
      "ease": 2.3,
      "reps": 0,
      "lapses": 0
    },
    {
      "id": "seed-0025",
      "de": "das Kleid",
      "en": "платье",
      "article": "",
      "notes": "",
      "created_at": "2026-03-25T19:10:00+00:00",
      "due_at": "2026-03-25T19:10:00+00:00",
      "interval_days": 0,
      "ease": 2.3,
      "reps": 0,
      "lapses": 0
    },
    {
      "id": "seed-0026",
      "de": "der Rock",
      "en": "юбка",
      "article": "",
      "notes": "",
      "created_at": "2026-03-25T19:10:00+00:00",
      "due_at": "2026-03-25T19:10:00+00:00",
      "interval_days": 0,
      "ease": 2.3,
      "reps": 0,
      "lapses": 0
    },
    {
      "id": "seed-0027",
      "de": "der König",
      "en": "король",
      "article": "",
      "notes": "",
      "created_at": "2026-03-25T19:10:00+00:00",
      "due_at": "2026-03-25T19:10:00+00:00",
      "interval_days": 0,
      "ease": 2.3,
      "reps": 0,
      "lapses": 0
    },
    {
      "id": "seed-0028",
      "de": "die Erfahrung",
      "en": "опыт",
      "article": "",
      "notes": "",
      "created_at": "2026-03-25T19:10:00+00:00",
      "due_at": "2026-03-25T19:10:00+00:00",
      "interval_days": 0,
      "ease": 2.3,
      "reps": 0,
      "lapses": 0
    },
    {
      "id": "seed-0029",
      "de": "die Tätigkeiten",
      "en": "деятельность, занятия",
      "article": "",
      "notes": "",
      "created_at": "2026-03-25T19:10:00+00:00",
      "due_at": "2026-03-25T19:10:00+00:00",
      "interval_days": 0,
      "ease": 2.3,
      "reps": 0,
      "lapses": 0
    },
    {
      "id": "seed-0030",
      "de": "das Angebot",
      "en": "предложение",
      "article": "",
      "notes": "",
      "created_at": "2026-03-25T19:10:00+00:00",
      "due_at": "2026-03-25T19:10:00+00:00",
      "interval_days": 0,
      "ease": 2.3,
      "reps": 0,
      "lapses": 0
    },
    {
      "id": "seed-0031",
      "de": "das Gerät",
      "en": "прибор, устройство",
      "article": "",
      "notes": "",
      "created_at": "2026-03-25T19:10:00+00:00",
      "due_at": "2026-03-26T19:55:36.275496+00:00",
      "interval_days": 1,
      "ease": 2.3,
      "reps": 1,
      "lapses": 0
    },
    {
      "id": "seed-0032",
      "de": "die Kraft",
      "en": "сила",
      "article": "",
      "notes": "",
      "created_at": "2026-03-25T19:10:00+00:00",
      "due_at": "2026-03-25T19:10:00+00:00",
      "interval_days": 0,
      "ease": 2.3,
      "reps": 0,
      "lapses": 0
    },
    {
      "id": "seed-0033",
      "de": "die Beratung",
      "en": "консультация",
      "article": "",
      "notes": "",
      "created_at": "2026-03-25T19:10:00+00:00",
      "due_at": "2026-03-25T19:10:00+00:00",
      "interval_days": 0,
      "ease": 2.3,
      "reps": 0,
      "lapses": 0
    },
    {
      "id": "seed-0034",
      "de": "die Welt",
      "en": "мир",
      "article": "",
      "notes": "",
      "created_at": "2026-03-25T19:10:00+00:00",
      "due_at": "2026-03-25T19:10:00+00:00",
      "interval_days": 0,
      "ease": 2.3,
      "reps": 0,
      "lapses": 0
    },
    {
      "id": "seed-0035",
      "de": "die Nachbarin",
      "en": "соседка",
      "article": "",
      "notes": "",
      "created_at": "2026-03-25T19:10:00+00:00",
      "due_at": "2026-03-25T19:10:00+00:00",
      "interval_days": 0,
      "ease": 2.3,
      "reps": 0,
      "lapses": 0
    },
    {
      "id": "seed-0036",
      "de": "der Nachbar",
      "en": "сосед",
      "article": "",
      "notes": "",
      "created_at": "2026-03-25T19:10:00+00:00",
      "due_at": "2026-03-25T19:10:00+00:00",
      "interval_days": 0,
      "ease": 2.3,
      "reps": 0,
      "lapses": 0
    },
    {
      "id": "seed-0037",
      "de": "der Wagen",
      "en": "автомобиль, повозка",
      "article": "",
      "notes": "",
      "created_at": "2026-03-25T19:10:00+00:00",
      "due_at": "2026-03-25T19:10:00+00:00",
      "interval_days": 0,
      "ease": 2.3,
      "reps": 0,
      "lapses": 0
    },
    {
      "id": "seed-0038",
      "de": "der Brief",
      "en": "письмо",
      "article": "",
      "notes": "",
      "created_at": "2026-03-25T19:10:00+00:00",
      "due_at": "2026-03-25T19:10:00+00:00",
      "interval_days": 0,
      "ease": 2.3,
      "reps": 0,
      "lapses": 0
    },
    {
      "id": "seed-0039",
      "de": "die Maus",
      "en": "мышь",
      "article": "",
      "notes": "",
      "created_at": "2026-03-25T19:10:00+00:00",
      "due_at": "2026-03-25T19:10:00+00:00",
      "interval_days": 0,
      "ease": 2.3,
      "reps": 0,
      "lapses": 0
    },
    {
      "id": "seed-0040",
      "de": "der Kater",
      "en": "кот; похмелье",
      "article": "",
      "notes": "",
      "created_at": "2026-03-25T19:10:00+00:00",
      "due_at": "2026-03-25T19:10:00+00:00",
      "interval_days": 0,
      "ease": 2.3,
      "reps": 0,
      "lapses": 0
    },
    {
      "id": "seed-0041",
      "de": "der Weg",
      "en": "путь, дорога",
      "article": "",
      "notes": "",
      "created_at": "2026-03-25T19:10:00+00:00",
      "due_at": "2026-03-25T19:10:00+00:00",
      "interval_days": 0,
      "ease": 2.3,
      "reps": 0,
      "lapses": 0
    },
    {
      "id": "seed-0042",
      "de": "der Ausflug",
      "en": "экскурсия, поездка",
      "article": "",
      "notes": "",
      "created_at": "2026-03-25T19:10:00+00:00",
      "due_at": "2026-03-25T19:10:00+00:00",
      "interval_days": 0,
      "ease": 2.3,
      "reps": 0,
      "lapses": 0
    },
    {
      "id": "seed-0043",
      "de": "der See",
      "en": "озеро",
      "article": "",
      "notes": "",
      "created_at": "2026-03-25T19:10:00+00:00",
      "due_at": "2026-03-25T19:10:00+00:00",
      "interval_days": 0,
      "ease": 2.3,
      "reps": 0,
      "lapses": 0
    },
    {
      "id": "seed-0044",
      "de": "der Feind",
      "en": "враг",
      "article": "",
      "notes": "",
      "created_at": "2026-03-25T19:10:00+00:00",
      "due_at": "2026-03-25T19:10:00+00:00",
      "interval_days": 0,
      "ease": 2.3,
      "reps": 0,
      "lapses": 0
    },
    {
      "id": "seed-0045",
      "de": "die Lust",
      "en": "желание, удовольствие",
      "article": "",
      "notes": "",
      "created_at": "2026-03-25T19:10:00+00:00",
      "due_at": "2026-03-25T19:10:00+00:00",
      "interval_days": 0,
      "ease": 2.3,
      "reps": 0,
      "lapses": 0
    },
    {
      "id": "seed-0046",
      "de": "die Kantine",
      "en": "столовая",
      "article": "",
      "notes": "",
      "created_at": "2026-03-25T19:10:00+00:00",
      "due_at": "2026-03-25T19:10:00+00:00",
      "interval_days": 0,
      "ease": 2.3,
      "reps": 0,
      "lapses": 0
    },
    {
      "id": "seed-0047",
      "de": "die Geschwister",
      "en": "братья и сёстры",
      "article": "",
      "notes": "",
      "created_at": "2026-03-25T19:10:00+00:00",
      "due_at": "2026-03-25T19:10:00+00:00",
      "interval_days": 0,
      "ease": 2.3,
      "reps": 0,
      "lapses": 0
    },
    {
      "id": "verb-0001",
      "de": "abdecken",
      "en": "накрывать (стол), покрывать",
      "article": "",
      "notes": "",
      "created_at": "2026-03-25T20:30:00+00:00",
      "due_at": "2026-03-25T20:30:00+00:00",
      "interval_days": 0,
      "ease": 2.3,
      "reps": 0,
      "lapses": 0
    },
    {
      "id": "verb-0002",
      "de": "abfahren",
      "en": "отправляться (о транспорте)",
      "article": "",
      "notes": "",
      "created_at": "2026-03-25T20:30:00+00:00",
      "due_at": "2026-03-25T20:30:00+00:00",
      "interval_days": 0,
      "ease": 2.3,
      "reps": 0,
      "lapses": 0
    },
    {
      "id": "verb-0003",
      "de": "abholen",
      "en": "забирать, встречать",
      "article": "",
      "notes": "",
      "created_at": "2026-03-25T20:30:00+00:00",
      "due_at": "2026-03-25T20:30:00+00:00",
      "interval_days": 0,
      "ease": 2.3,
      "reps": 0,
      "lapses": 0
    },
    {
      "id": "verb-0004",
      "de": "abreisen",
      "en": "уезжать",
      "article": "",
      "notes": "",
      "created_at": "2026-03-25T20:30:00+00:00",
      "due_at": "2026-03-25T20:30:00+00:00",
      "interval_days": 0,
      "ease": 2.3,
      "reps": 0,
      "lapses": 0
    },
    {
      "id": "verb-0005",
      "de": "abschreiben",
      "en": "списывать",
      "article": "",
      "notes": "",
      "created_at": "2026-03-25T20:30:00+00:00",
      "due_at": "2026-03-25T20:30:00+00:00",
      "interval_days": 0,
      "ease": 2.3,
      "reps": 0,
      "lapses": 0
    },
    {
      "id": "verb-0006",
      "de": "angehen",
      "en": "касаться, затрагивать",
      "article": "",
      "notes": "",
      "created_at": "2026-03-25T20:30:00+00:00",
      "due_at": "2026-03-25T20:30:00+00:00",
      "interval_days": 0,
      "ease": 2.3,
      "reps": 0,
      "lapses": 0
    },
    {
      "id": "verb-0007",
      "de": "anfangen",
      "en": "начинать",
      "article": "",
      "notes": "",
      "created_at": "2026-03-25T20:30:00+00:00",
      "due_at": "2026-03-25T20:30:00+00:00",
      "interval_days": 0,
      "ease": 2.3,
      "reps": 0,
      "lapses": 0
    },
    {
      "id": "verb-0008",
      "de": "ankommen",
      "en": "прибывать",
      "article": "",
      "notes": "",
      "created_at": "2026-03-25T20:30:00+00:00",
      "due_at": "2026-03-25T20:30:00+00:00",
      "interval_days": 0,
      "ease": 2.3,
      "reps": 0,
      "lapses": 0
    },
    {
      "id": "verb-0009",
      "de": "anmachen",
      "en": "включать",
      "article": "",
      "notes": "",
      "created_at": "2026-03-25T20:30:00+00:00",
      "due_at": "2026-03-25T20:30:00+00:00",
      "interval_days": 0,
      "ease": 2.3,
      "reps": 0,
      "lapses": 0
    },
    {
      "id": "verb-0010",
      "de": "anrufen",
      "en": "звонить",
      "article": "",
      "notes": "",
      "created_at": "2026-03-25T20:30:00+00:00",
      "due_at": "2026-03-25T20:30:00+00:00",
      "interval_days": 0,
      "ease": 2.3,
      "reps": 0,
      "lapses": 0
    },
    {
      "id": "verb-0011",
      "de": "anschauen",
      "en": "смотреть",
      "article": "",
      "notes": "",
      "created_at": "2026-03-25T20:30:00+00:00",
      "due_at": "2026-03-25T20:30:00+00:00",
      "interval_days": 0,
      "ease": 2.3,
      "reps": 0,
      "lapses": 0
    },
    {
      "id": "verb-0012",
      "de": "anziehen",
      "en": "одевать (кого-то) / надевать",
      "article": "",
      "notes": "",
      "created_at": "2026-03-25T20:30:00+00:00",
      "due_at": "2026-03-25T20:30:00+00:00",
      "interval_days": 0,
      "ease": 2.3,
      "reps": 0,
      "lapses": 0
    },
    {
      "id": "verb-0013",
      "de": "anzünden",
      "en": "поджигать",
      "article": "",
      "notes": "",
      "created_at": "2026-03-25T20:30:00+00:00",
      "due_at": "2026-03-25T20:30:00+00:00",
      "interval_days": 0,
      "ease": 2.3,
      "reps": 0,
      "lapses": 0
    },
    {
      "id": "verb-0014",
      "de": "aufhängen",
      "en": "вешать",
      "article": "",
      "notes": "",
      "created_at": "2026-03-25T20:30:00+00:00",
      "due_at": "2026-03-25T20:30:00+00:00",
      "interval_days": 0,
      "ease": 2.3,
      "reps": 0,
      "lapses": 0
    },
    {
      "id": "verb-0015",
      "de": "aufmachen",
      "en": "открывать",
      "article": "",
      "notes": "",
      "created_at": "2026-03-25T20:30:00+00:00",
      "due_at": "2026-03-25T20:30:00+00:00",
      "interval_days": 0,
      "ease": 2.3,
      "reps": 0,
      "lapses": 0
    },
    {
      "id": "verb-0016",
      "de": "aufstehen",
      "en": "вставать",
      "article": "",
      "notes": "",
      "created_at": "2026-03-25T20:30:00+00:00",
      "due_at": "2026-04-16T20:26:47.260362+00:00",
      "interval_days": 1,
      "ease": 2.3,
      "reps": 1,
      "lapses": 0
    },
    {
      "id": "verb-0017",
      "de": "aufwachen",
      "en": "просыпаться",
      "article": "",
      "notes": "",
      "created_at": "2026-03-25T20:30:00+00:00",
      "due_at": "2026-03-25T20:30:00+00:00",
      "interval_days": 0,
      "ease": 2.3,
      "reps": 0,
      "lapses": 0
    },
    {
      "id": "verb-0018",
      "de": "ausfüllen",
      "en": "заполнять",
      "article": "",
      "notes": "",
      "created_at": "2026-03-25T20:30:00+00:00",
      "due_at": "2026-03-25T20:30:00+00:00",
      "interval_days": 0,
      "ease": 2.3,
      "reps": 0,
      "lapses": 0
    },
    {
      "id": "verb-0019",
      "de": "ausgehen",
      "en": "выходить / гаснуть",
      "article": "",
      "notes": "",
      "created_at": "2026-03-25T20:30:00+00:00",
      "due_at": "2026-03-25T20:30:00+00:00",
      "interval_days": 0,
      "ease": 2.3,
      "reps": 0,
      "lapses": 0
    },
    {
      "id": "verb-0020",
      "de": "ausmachen",
      "en": "выключать / договариваться",
      "article": "",
      "notes": "",
      "created_at": "2026-03-25T20:30:00+00:00",
      "due_at": "2026-03-25T20:30:00+00:00",
      "interval_days": 0,
      "ease": 2.3,
      "reps": 0,
      "lapses": 0
    },
    {
      "id": "verb-0021",
      "de": "aussehen",
      "en": "выглядеть",
      "article": "",
      "notes": "",
      "created_at": "2026-03-25T20:30:00+00:00",
      "due_at": "2026-03-25T20:30:00+00:00",
      "interval_days": 0,
      "ease": 2.3,
      "reps": 0,
      "lapses": 0
    },
    {
      "id": "verb-0022",
      "de": "ausschalten",
      "en": "выключать",
      "article": "",
      "notes": "",
      "created_at": "2026-03-25T20:30:00+00:00",
      "due_at": "2026-03-25T20:30:00+00:00",
      "interval_days": 0,
      "ease": 2.3,
      "reps": 0,
      "lapses": 0
    },
    {
      "id": "verb-0023",
      "de": "ausziehen",
      "en": "снимать одежду / съезжать",
      "article": "",
      "notes": "",
      "created_at": "2026-03-25T20:30:00+00:00",
      "due_at": "2026-03-25T20:30:00+00:00",
      "interval_days": 0,
      "ease": 2.3,
      "reps": 0,
      "lapses": 0
    },
    {
      "id": "verb-0024",
      "de": "austoben",
      "en": "выплеснуть энергию",
      "article": "",
      "notes": "",
      "created_at": "2026-03-25T20:30:00+00:00",
      "due_at": "2026-03-25T20:30:00+00:00",
      "interval_days": 0,
      "ease": 2.3,
      "reps": 0,
      "lapses": 0
    },
    {
      "id": "verb-0025",
      "de": "einkaufen",
      "en": "делать покупки",
      "article": "",
      "notes": "",
      "created_at": "2026-03-25T20:30:00+00:00",
      "due_at": "2026-03-25T20:30:00+00:00",
      "interval_days": 0,
      "ease": 2.3,
      "reps": 0,
      "lapses": 0
    },
    {
      "id": "verb-0026",
      "de": "einladen",
      "en": "приглашать",
      "article": "",
      "notes": "",
      "created_at": "2026-03-25T20:30:00+00:00",
      "due_at": "2026-03-25T20:30:00+00:00",
      "interval_days": 0,
      "ease": 2.3,
      "reps": 0,
      "lapses": 0
    },
    {
      "id": "verb-0027",
      "de": "einschalten",
      "en": "включать",
      "article": "",
      "notes": "",
      "created_at": "2026-03-25T20:30:00+00:00",
      "due_at": "2026-03-25T20:30:00+00:00",
      "interval_days": 0,
      "ease": 2.3,
      "reps": 0,
      "lapses": 0
    },
    {
      "id": "verb-0028",
      "de": "einschlafen",
      "en": "засыпать",
      "article": "",
      "notes": "",
      "created_at": "2026-03-25T20:30:00+00:00",
      "due_at": "2026-03-25T20:30:00+00:00",
      "interval_days": 0,
      "ease": 2.3,
      "reps": 0,
      "lapses": 0
    },
    {
      "id": "verb-0029",
      "de": "einziehen",
      "en": "въезжать",
      "article": "",
      "notes": "",
      "created_at": "2026-03-25T20:30:00+00:00",
      "due_at": "2026-03-25T20:30:00+00:00",
      "interval_days": 0,
      "ease": 2.3,
      "reps": 0,
      "lapses": 0
    },
    {
      "id": "verb-0030",
      "de": "heimgehen",
      "en": "идти домой",
      "article": "",
      "notes": "",
      "created_at": "2026-03-25T20:30:00+00:00",
      "due_at": "2026-03-25T20:30:00+00:00",
      "interval_days": 0,
      "ease": 2.3,
      "reps": 0,
      "lapses": 0
    },
    {
      "id": "verb-0031",
      "de": "herauskommen",
      "en": "выходить наружу",
      "article": "",
      "notes": "",
      "created_at": "2026-03-25T20:30:00+00:00",
      "due_at": "2026-03-25T20:30:00+00:00",
      "interval_days": 0,
      "ease": 2.3,
      "reps": 0,
      "lapses": 0
    },
    {
      "id": "verb-0032",
      "de": "herkommen",
      "en": "приходить сюда",
      "article": "",
      "notes": "",
      "created_at": "2026-03-25T20:30:00+00:00",
      "due_at": "2026-03-25T20:30:00+00:00",
      "interval_days": 0,
      "ease": 2.3,
      "reps": 0,
      "lapses": 0
    },
    {
      "id": "verb-0033",
      "de": "losfahren",
      "en": "отправляться (на транспорте)",
      "article": "",
      "notes": "",
      "created_at": "2026-03-25T20:30:00+00:00",
      "due_at": "2026-03-25T20:30:00+00:00",
      "interval_days": 0,
      "ease": 2.3,
      "reps": 0,
      "lapses": 0
    },
    {
      "id": "verb-0034",
      "de": "losgehen",
      "en": "отправляться / начинаться",
      "article": "",
      "notes": "",
      "created_at": "2026-03-25T20:30:00+00:00",
      "due_at": "2026-03-25T20:30:00+00:00",
      "interval_days": 0,
      "ease": 2.3,
      "reps": 0,
      "lapses": 0
    },
    {
      "id": "verb-0035",
      "de": "mitarbeiten",
      "en": "сотрудничать",
      "article": "",
      "notes": "",
      "created_at": "2026-03-25T20:30:00+00:00",
      "due_at": "2026-03-25T20:30:00+00:00",
      "interval_days": 0,
      "ease": 2.3,
      "reps": 0,
      "lapses": 0
    },
    {
      "id": "verb-0036",
      "de": "mitbringen",
      "en": "приносить с собой",
      "article": "",
      "notes": "",
      "created_at": "2026-03-25T20:30:00+00:00",
      "due_at": "2026-03-25T20:30:00+00:00",
      "interval_days": 0,
      "ease": 2.3,
      "reps": 0,
      "lapses": 0
    },
    {
      "id": "verb-0037",
      "de": "mitkommen",
      "en": "идти/ехать вместе",
      "article": "",
      "notes": "",
      "created_at": "2026-03-25T20:30:00+00:00",
      "due_at": "2026-03-25T20:30:00+00:00",
      "interval_days": 0,
      "ease": 2.3,
      "reps": 0,
      "lapses": 0
    },
    {
      "id": "verb-0038",
      "de": "nachdenken",
      "en": "размышлять",
      "article": "",
      "notes": "",
      "created_at": "2026-03-25T20:30:00+00:00",
      "due_at": "2026-03-25T20:30:00+00:00",
      "interval_days": 0,
      "ease": 2.3,
      "reps": 0,
      "lapses": 0
    },
    {
      "id": "verb-0039",
      "de": "nachschauen",
      "en": "проверять, посмотреть",
      "article": "",
      "notes": "",
      "created_at": "2026-03-25T20:30:00+00:00",
      "due_at": "2026-03-25T20:30:00+00:00",
      "interval_days": 0,
      "ease": 2.3,
      "reps": 0,
      "lapses": 0
    },
    {
      "id": "verb-0040",
      "de": "umziehen",
      "en": "переезжать / переодеваться",
      "article": "",
      "notes": "",
      "created_at": "2026-03-25T20:30:00+00:00",
      "due_at": "2026-03-25T20:30:00+00:00",
      "interval_days": 0,
      "ease": 2.3,
      "reps": 0,
      "lapses": 0
    },
    {
      "id": "verb-0041",
      "de": "vorbeikommen",
      "en": "заходить, заезжать",
      "article": "",
      "notes": "",
      "created_at": "2026-03-25T20:30:00+00:00",
      "due_at": "2026-03-25T20:30:00+00:00",
      "interval_days": 0,
      "ease": 2.3,
      "reps": 0,
      "lapses": 0
    },
    {
      "id": "verb-0042",
      "de": "vorhaben",
      "en": "намереваться",
      "article": "",
      "notes": "",
      "created_at": "2026-03-25T20:30:00+00:00",
      "due_at": "2026-03-25T20:30:00+00:00",
      "interval_days": 0,
      "ease": 2.3,
      "reps": 0,
      "lapses": 0
    },
    {
      "id": "verb-0043",
      "de": "weggehen",
      "en": "уходить",
      "article": "",
      "notes": "",
      "created_at": "2026-03-25T20:30:00+00:00",
      "due_at": "2026-03-25T20:30:00+00:00",
      "interval_days": 0,
      "ease": 2.3,
      "reps": 0,
      "lapses": 0
    },
    {
      "id": "verb-0044",
      "de": "zuhören",
      "en": "слушать (внимательно)",
      "article": "",
      "notes": "",
      "created_at": "2026-03-25T20:30:00+00:00",
      "due_at": "2026-03-25T20:30:00+00:00",
      "interval_days": 0,
      "ease": 2.3,
      "reps": 0,
      "lapses": 0
    },
    {
      "id": "verb-0045",
      "de": "zumachen",
      "en": "закрывать",
      "article": "",
      "notes": "",
      "created_at": "2026-03-25T20:30:00+00:00",
      "due_at": "2026-03-25T20:30:00+00:00",
      "interval_days": 0,
      "ease": 2.3,
      "reps": 0,
      "lapses": 0
    },
    {
      "id": "verb-0046",
      "de": "zurückkommen",
      "en": "возвращаться",
      "article": "",
      "notes": "",
      "created_at": "2026-03-25T20:30:00+00:00",
      "due_at": "2026-03-25T20:30:00+00:00",
      "interval_days": 0,
      "ease": 2.3,
      "reps": 0,
      "lapses": 0
    },
    {
      "id": "verb-0047",
      "de": "wehtun",
      "en": "болеть (причинять боль)",
      "article": "",
      "notes": "",
      "created_at": "2026-03-25T20:30:00+00:00",
      "due_at": "2026-03-25T20:30:00+00:00",
      "interval_days": 0,
      "ease": 2.3,
      "reps": 0,
      "lapses": 0
    },
    {
      "id": "verb-0048",
      "de": "stattfinden",
      "en": "происходить, состояться",
      "article": "",
      "notes": "",
      "created_at": "2026-03-25T20:30:00+00:00",
      "due_at": "2026-03-25T20:30:00+00:00",
      "interval_days": 0,
      "ease": 2.3,
      "reps": 0,
      "lapses": 0
    },
    {
      "id": "verb-0049",
      "de": "wegwerfen",
      "en": "выбрасывать",
      "article": "",
      "notes": "",
      "created_at": "2026-03-25T20:30:00+00:00",
      "due_at": "2026-03-25T20:30:00+00:00",
      "interval_days": 0,
      "ease": 2.3,
      "reps": 0,
      "lapses": 0
    },
    {
      "id": "verb-0050",
      "de": "mischen",
      "en": "смешивать",
      "article": "",
      "notes": "",
      "created_at": "2026-03-25T20:30:00+00:00",
      "due_at": "2026-04-18T20:29:20.488689+00:00",
      "interval_days": 3,
      "ease": 2.3,
      "reps": 2,
      "lapses": 0
    },
    {
      "id": "verb-0051",
      "de": "ergänzen",
      "en": "дополнять",
      "article": "",
      "notes": "",
      "created_at": "2026-03-25T20:30:00+00:00",
      "due_at": "2026-03-25T20:30:00+00:00",
      "interval_days": 0,
      "ease": 2.3,
      "reps": 0,
      "lapses": 0
    },
    {
      "id": "verb-0052",
      "de": "legen",
      "en": "класть (горизонтально)",
      "article": "",
      "notes": "",
      "created_at": "2026-03-25T20:30:00+00:00",
      "due_at": "2026-03-25T20:30:00+00:00",
      "interval_days": 0,
      "ease": 2.3,
      "reps": 0,
      "lapses": 0
    },
    {
      "id": "verb-0053",
      "de": "zeigen",
      "en": "показывать",
      "article": "",
      "notes": "",
      "created_at": "2026-03-25T20:30:00+00:00",
      "due_at": "2026-03-25T20:30:00+00:00",
      "interval_days": 0,
      "ease": 2.3,
      "reps": 0,
      "lapses": 0
    },
    {
      "id": "verb-0054",
      "de": "töten",
      "en": "убивать",
      "article": "",
      "notes": "",
      "created_at": "2026-03-25T20:30:00+00:00",
      "due_at": "2026-03-25T20:30:00+00:00",
      "interval_days": 0,
      "ease": 2.3,
      "reps": 0,
      "lapses": 0
    },
    {
      "id": "verb-0055",
      "de": "bekommen",
      "en": "получать",
      "article": "",
      "notes": "",
      "created_at": "2026-03-25T20:30:00+00:00",
      "due_at": "2026-03-25T20:30:00+00:00",
      "interval_days": 0,
      "ease": 2.3,
      "reps": 0,
      "lapses": 0
    },
    {
      "id": "verb-0056",
      "de": "wiederholen",
      "en": "повторять",
      "article": "",
      "notes": "",
      "created_at": "2026-03-25T20:30:00+00:00",
      "due_at": "2026-03-25T20:30:00+00:00",
      "interval_days": 0,
      "ease": 2.3,
      "reps": 0,
      "lapses": 0
    },
    {
      "id": "verb-0057",
      "de": "erklären",
      "en": "объяснять",
      "article": "",
      "notes": "",
      "created_at": "2026-03-25T20:30:00+00:00",
      "due_at": "2026-03-25T20:30:00+00:00",
      "interval_days": 0,
      "ease": 2.3,
      "reps": 0,
      "lapses": 0
    },
    {
      "id": "verb-0058",
      "de": "schenken",
      "en": "дарить",
      "article": "",
      "notes": "",
      "created_at": "2026-03-25T20:30:00+00:00",
      "due_at": "2026-03-25T20:30:00+00:00",
      "interval_days": 0,
      "ease": 2.3,
      "reps": 0,
      "lapses": 0
    },
    {
      "id": "verb-0059",
      "de": "küssen",
      "en": "целовать",
      "article": "",
      "notes": "",
      "created_at": "2026-03-25T20:30:00+00:00",
      "due_at": "2026-03-25T20:30:00+00:00",
      "interval_days": 0,
      "ease": 2.3,
      "reps": 0,
      "lapses": 0
    },
    {
      "id": "verb-0060",
      "de": "gratulieren",
      "en": "поздравлять",
      "article": "",
      "notes": "",
      "created_at": "2026-03-25T20:30:00+00:00",
      "due_at": "2026-03-25T20:30:00+00:00",
      "interval_days": 0,
      "ease": 2.3,
      "reps": 0,
      "lapses": 0
    },
    {
      "id": "verb-0061",
      "de": "reparieren",
      "en": "чинить",
      "article": "",
      "notes": "",
      "created_at": "2026-03-25T20:30:00+00:00",
      "due_at": "2026-03-25T20:30:00+00:00",
      "interval_days": 0,
      "ease": 2.3,
      "reps": 0,
      "lapses": 0
    },
    {
      "id": "verb-0062",
      "de": "übernachten",
      "en": "переночевать",
      "article": "",
      "notes": "",
      "created_at": "2026-03-25T20:30:00+00:00",
      "due_at": "2026-03-25T20:30:00+00:00",
      "interval_days": 0,
      "ease": 2.3,
      "reps": 0,
      "lapses": 0
    },
    {
      "id": "verb-0063",
      "de": "weinen",
      "en": "плакать",
      "article": "",
      "notes": "",
      "created_at": "2026-03-25T20:30:00+00:00",
      "due_at": "2026-03-25T20:30:00+00:00",
      "interval_days": 0,
      "ease": 2.3,
      "reps": 0,
      "lapses": 0
    },
    {
      "id": "bulk-1774469374358",
      "de": "beeil dich",
      "en": "поторопись",
      "article": "",
      "notes": "",
      "created_at": "2026-03-25T20:09:34.357931+00:00",
      "due_at": "2026-03-25T20:09:34.357931+00:00",
      "interval_days": 0,
      "ease": 2.3,
      "reps": 0,
      "lapses": 0
    },
    {
      "id": "bulk-1774469374359",
      "de": "wirklich Pech",
      "en": "действительно не везёт / вот неудача",
      "article": "",
      "notes": "",
      "created_at": "2026-03-25T20:09:34.357931+00:00",
      "due_at": "2026-03-25T20:09:34.357931+00:00",
      "interval_days": 0,
      "ease": 2.3,
      "reps": 0,
      "lapses": 0
    },
    {
      "id": "bulk-1774469374360",
      "de": "bald",
      "en": "скоро",
      "article": "",
      "notes": "",
      "created_at": "2026-03-25T20:09:34.357931+00:00",
      "due_at": "2026-03-25T20:09:34.357931+00:00",
      "interval_days": 0,
      "ease": 2.3,
      "reps": 0,
      "lapses": 0
    },
    {
      "id": "bulk-1774469374361",
      "de": "wütend",
      "en": "злой",
      "article": "",
      "notes": "",
      "created_at": "2026-03-25T20:09:34.357931+00:00",
      "due_at": "2026-03-25T20:09:34.357931+00:00",
      "interval_days": 0,
      "ease": 2.3,
      "reps": 0,
      "lapses": 0
    },
    {
      "id": "bulk-1774469374362",
      "de": "verschwindet",
      "en": "исчезает",
      "article": "",
      "notes": "",
      "created_at": "2026-03-25T20:09:34.357931+00:00",
      "due_at": "2026-03-25T20:09:34.357931+00:00",
      "interval_days": 0,
      "ease": 2.3,
      "reps": 0,
      "lapses": 0
    },
    {
      "id": "bulk-1774469374363",
      "de": "endlich",
      "en": "наконец-то",
      "article": "",
      "notes": "",
      "created_at": "2026-03-25T20:09:34.357931+00:00",
      "due_at": "2026-03-25T20:09:34.357931+00:00",
      "interval_days": 0,
      "ease": 2.3,
      "reps": 0,
      "lapses": 0
    },
    {
      "id": "bulk-1774469374364",
      "de": "etwas",
      "en": "что-то / немного",
      "article": "",
      "notes": "",
      "created_at": "2026-03-25T20:09:34.357931+00:00",
      "due_at": "2026-03-25T20:09:34.357931+00:00",
      "interval_days": 0,
      "ease": 2.3,
      "reps": 0,
      "lapses": 0
    },
    {
      "id": "bulk-1774469374365",
      "de": "täglich",
      "en": "ежедневно",
      "article": "",
      "notes": "",
      "created_at": "2026-03-25T20:09:34.357931+00:00",
      "due_at": "2026-03-25T20:09:34.357931+00:00",
      "interval_days": 0,
      "ease": 2.3,
      "reps": 0,
      "lapses": 0
    },
    {
      "id": "bulk-1774469374366",
      "de": "schmutzig",
      "en": "грязный",
      "article": "",
      "notes": "",
      "created_at": "2026-03-25T20:09:34.357931+00:00",
      "due_at": "2026-03-25T20:09:34.357931+00:00",
      "interval_days": 0,
      "ease": 2.3,
      "reps": 0,
      "lapses": 0
    },
    {
      "id": "bulk-1774469374367",
      "de": "gleich",
      "en": "сейчас / сразу / одинаковый (по контексту)",
      "article": "",
      "notes": "",
      "created_at": "2026-03-25T20:09:34.357931+00:00",
      "due_at": "2026-03-25T20:09:34.357931+00:00",
      "interval_days": 0,
      "ease": 2.3,
      "reps": 0,
      "lapses": 0
    },
    {
      "id": "bulk-1774469374368",
      "de": "wahrscheinlich",
      "en": "вероятно",
      "article": "",
      "notes": "",
      "created_at": "2026-03-25T20:09:34.357931+00:00",
      "due_at": "2026-03-25T20:09:34.357931+00:00",
      "interval_days": 0,
      "ease": 2.3,
      "reps": 0,
      "lapses": 0
    },
    {
      "id": "bulk-1774469374369",
      "de": "nur",
      "en": "только",
      "article": "",
      "notes": "",
      "created_at": "2026-03-25T20:09:34.357931+00:00",
      "due_at": "2026-03-25T20:09:34.357931+00:00",
      "interval_days": 0,
      "ease": 2.3,
      "reps": 0,
      "lapses": 0
    },
    {
      "id": "bulk-1774469374370",
      "de": "wieder",
      "en": "снова / опять",
      "article": "",
      "notes": "",
      "created_at": "2026-03-25T20:09:34.357931+00:00",
      "due_at": "2026-03-25T20:09:34.357931+00:00",
      "interval_days": 0,
      "ease": 2.3,
      "reps": 0,
      "lapses": 0
    },
    {
      "id": "bulk-1774469374371",
      "de": "leer",
      "en": "пустой",
      "article": "",
      "notes": "",
      "created_at": "2026-03-25T20:09:34.357931+00:00",
      "due_at": "2026-03-25T20:09:34.357931+00:00",
      "interval_days": 0,
      "ease": 2.3,
      "reps": 0,
      "lapses": 0
    },
    {
      "id": "bulk-1774469374372",
      "de": "doch",
      "en": "всё-таки / же / нет (ответ на отрицание)",
      "article": "",
      "notes": "",
      "created_at": "2026-03-25T20:09:34.357931+00:00",
      "due_at": "2026-03-25T20:09:34.357931+00:00",
      "interval_days": 0,
      "ease": 2.3,
      "reps": 0,
      "lapses": 0
    },
    {
      "id": "bulk-1774469374373",
      "de": "seit",
      "en": "с (какого-то времени)",
      "article": "",
      "notes": "",
      "created_at": "2026-03-25T20:09:34.357931+00:00",
      "due_at": "2026-03-25T20:09:34.357931+00:00",
      "interval_days": 0,
      "ease": 2.3,
      "reps": 0,
      "lapses": 0
    },
    {
      "id": "bulk-1774469374374",
      "de": "hoch",
      "en": "высокий",
      "article": "",
      "notes": "",
      "created_at": "2026-03-25T20:09:34.357931+00:00",
      "due_at": "2026-03-25T20:09:34.357931+00:00",
      "interval_days": 0,
      "ease": 2.3,
      "reps": 0,
      "lapses": 0
    },
    {
      "id": "bulk-1774469374375",
      "de": "liegen",
      "en": "лежать / находиться",
      "article": "",
      "notes": "",
      "created_at": "2026-03-25T20:09:34.357931+00:00",
      "due_at": "2026-03-25T20:09:34.357931+00:00",
      "interval_days": 0,
      "ease": 2.3,
      "reps": 0,
      "lapses": 0
    },
    {
      "id": "bulk-1774469374376",
      "de": "auf dem Land",
      "en": "за городом / в сельской местности",
      "article": "",
      "notes": "",
      "created_at": "2026-03-25T20:09:34.357931+00:00",
      "due_at": "2026-03-25T20:09:34.357931+00:00",
      "interval_days": 0,
      "ease": 2.3,
      "reps": 0,
      "lapses": 0
    },
    {
      "id": "bulk-1774469374377",
      "de": "genauso",
      "en": "так же",
      "article": "",
      "notes": "",
      "created_at": "2026-03-25T20:09:34.357931+00:00",
      "due_at": "2026-03-25T20:09:34.357931+00:00",
      "interval_days": 0,
      "ease": 2.3,
      "reps": 0,
      "lapses": 0
    },
    {
      "id": "bulk-1774469374378",
      "de": "welche",
      "en": "какой / какие",
      "article": "",
      "notes": "",
      "created_at": "2026-03-25T20:09:34.357931+00:00",
      "due_at": "2026-03-25T20:09:34.357931+00:00",
      "interval_days": 0,
      "ease": 2.3,
      "reps": 0,
      "lapses": 0
    },
    {
      "id": "bulk-1774469374379",
      "de": "guck mal",
      "en": "посмотри",
      "article": "",
      "notes": "",
      "created_at": "2026-03-25T20:09:34.357931+00:00",
      "due_at": "2026-03-25T20:09:34.357931+00:00",
      "interval_days": 0,
      "ease": 2.3,
      "reps": 0,
      "lapses": 0
    },
    {
      "id": "bulk-1774469374380",
      "de": "tut weh",
      "en": "болит",
      "article": "",
      "notes": "",
      "created_at": "2026-03-25T20:09:34.357931+00:00",
      "due_at": "2026-03-25T20:09:34.357931+00:00",
      "interval_days": 0,
      "ease": 2.3,
      "reps": 0,
      "lapses": 0
    },
    {
      "id": "bulk-1774469374381",
      "de": "weniger",
      "en": "меньше",
      "article": "",
      "notes": "",
      "created_at": "2026-03-25T20:09:34.357931+00:00",
      "due_at": "2026-03-25T20:09:34.357931+00:00",
      "interval_days": 0,
      "ease": 2.3,
      "reps": 0,
      "lapses": 0
    },
    {
      "id": "bulk-1774469374382",
      "de": "wenig",
      "en": "мало",
      "article": "",
      "notes": "",
      "created_at": "2026-03-25T20:09:34.357931+00:00",
      "due_at": "2026-03-25T20:09:34.357931+00:00",
      "interval_days": 0,
      "ease": 2.3,
      "reps": 0,
      "lapses": 0
    },
    {
      "id": "bulk-1774469374383",
      "de": "langweilig",
      "en": "скучный",
      "article": "",
      "notes": "",
      "created_at": "2026-03-25T20:09:34.357931+00:00",
      "due_at": "2026-03-25T20:09:34.357931+00:00",
      "interval_days": 0,
      "ease": 2.3,
      "reps": 0,
      "lapses": 0
    },
    {
      "id": "bulk-1774469374384",
      "de": "reich",
      "en": "богатый",
      "article": "",
      "notes": "",
      "created_at": "2026-03-25T20:09:34.357931+00:00",
      "due_at": "2026-03-25T20:09:34.357931+00:00",
      "interval_days": 0,
      "ease": 2.3,
      "reps": 0,
      "lapses": 0
    },
    {
      "id": "bulk-1774469374385",
      "de": "war",
      "en": "был",
      "article": "",
      "notes": "",
      "created_at": "2026-03-25T20:09:34.357931+00:00",
      "due_at": "2026-03-25T20:09:34.357931+00:00",
      "interval_days": 0,
      "ease": 2.3,
      "reps": 0,
      "lapses": 0
    },
    {
      "id": "bulk-1774469374386",
      "de": "halb",
      "en": "половина / наполовину",
      "article": "",
      "notes": "",
      "created_at": "2026-03-25T20:09:34.357931+00:00",
      "due_at": "2026-03-25T20:09:34.357931+00:00",
      "interval_days": 0,
      "ease": 2.3,
      "reps": 0,
      "lapses": 0
    },
    {
      "id": "bulk-1774469374387",
      "de": "gültig",
      "en": "действительный / действующий",
      "article": "",
      "notes": "",
      "created_at": "2026-03-25T20:09:34.357931+00:00",
      "due_at": "2026-03-25T20:09:34.357931+00:00",
      "interval_days": 0,
      "ease": 2.3,
      "reps": 0,
      "lapses": 0
    },
    {
      "id": "bulk-1774469374388",
      "de": "ganz",
      "en": "весь / полностью",
      "article": "",
      "notes": "",
      "created_at": "2026-03-25T20:09:34.357931+00:00",
      "due_at": "2026-03-25T20:09:34.357931+00:00",
      "interval_days": 0,
      "ease": 2.3,
      "reps": 0,
      "lapses": 0
    },
    {
      "id": "bulk-1774469374389",
      "de": "dort",
      "en": "там",
      "article": "",
      "notes": "",
      "created_at": "2026-03-25T20:09:34.357931+00:00",
      "due_at": "2026-03-25T20:09:34.357931+00:00",
      "interval_days": 0,
      "ease": 2.3,
      "reps": 0,
      "lapses": 0
    },
    {
      "id": "bulk-1774469374390",
      "de": "manche",
      "en": "некоторые",
      "article": "",
      "notes": "",
      "created_at": "2026-03-25T20:09:34.357931+00:00",
      "due_at": "2026-03-25T20:09:34.357931+00:00",
      "interval_days": 0,
      "ease": 2.3,
      "reps": 0,
      "lapses": 0
    },
    {
      "id": "bulk-1774469374391",
      "de": "weit",
      "en": "далеко",
      "article": "",
      "notes": "",
      "created_at": "2026-03-25T20:09:34.357931+00:00",
      "due_at": "2026-03-25T20:09:34.357931+00:00",
      "interval_days": 0,
      "ease": 2.3,
      "reps": 0,
      "lapses": 0
    },
    {
      "id": "bulk-1774469374392",
      "de": "sogar",
      "en": "даже",
      "article": "",
      "notes": "",
      "created_at": "2026-03-25T20:09:34.357931+00:00",
      "due_at": "2026-03-25T20:09:34.357931+00:00",
      "interval_days": 0,
      "ease": 2.3,
      "reps": 0,
      "lapses": 0
    },
    {
      "id": "bulk-1774469374393",
      "de": "weil",
      "en": "потому что",
      "article": "",
      "notes": "",
      "created_at": "2026-03-25T20:09:34.357931+00:00",
      "due_at": "2026-03-25T20:09:34.357931+00:00",
      "interval_days": 0,
      "ease": 2.3,
      "reps": 0,
      "lapses": 0
    },
    {
      "id": "bulk-1774469374394",
      "de": "zurzeit",
      "en": "сейчас / в данный момент",
      "article": "",
      "notes": "",
      "created_at": "2026-03-25T20:09:34.357931+00:00",
      "due_at": "2026-03-25T20:09:34.357931+00:00",
      "interval_days": 0,
      "ease": 2.3,
      "reps": 0,
      "lapses": 0
    },
    {
      "id": "bulk-1774469374395",
      "de": "schlank",
      "en": "стройный",
      "article": "",
      "notes": "",
      "created_at": "2026-03-25T20:09:34.357931+00:00",
      "due_at": "2026-03-25T20:09:34.357931+00:00",
      "interval_days": 0,
      "ease": 2.3,
      "reps": 0,
      "lapses": 0
    },
    {
      "id": "bulk-1774469374396",
      "de": "gezogen",
      "en": "переехал (от ziehen)",
      "article": "",
      "notes": "",
      "created_at": "2026-03-25T20:09:34.357931+00:00",
      "due_at": "2026-03-25T20:09:34.357931+00:00",
      "interval_days": 0,
      "ease": 2.3,
      "reps": 0,
      "lapses": 0
    },
    {
      "id": "bulk-1774469374397",
      "de": "gekündigt",
      "en": "уволился / расторг контракт",
      "article": "",
      "notes": "",
      "created_at": "2026-03-25T20:09:34.357931+00:00",
      "due_at": "2026-03-25T20:09:34.357931+00:00",
      "interval_days": 0,
      "ease": 2.3,
      "reps": 0,
      "lapses": 0
    },
    {
      "id": "bulk-1774469374398",
      "de": "zufrieden",
      "en": "довольный",
      "article": "",
      "notes": "",
      "created_at": "2026-03-25T20:09:34.357931+00:00",
      "due_at": "2026-03-25T20:09:34.357931+00:00",
      "interval_days": 0,
      "ease": 2.3,
      "reps": 0,
      "lapses": 0
    },
    {
      "id": "bulk-1774469374399",
      "de": "still",
      "en": "тихий / спокойный",
      "article": "",
      "notes": "",
      "created_at": "2026-03-25T20:09:34.357931+00:00",
      "due_at": "2026-03-25T20:09:34.357931+00:00",
      "interval_days": 0,
      "ease": 2.3,
      "reps": 0,
      "lapses": 0
    },
    {
      "id": "bulk-1774469374400",
      "de": "übrigens",
      "en": "кстати",
      "article": "",
      "notes": "",
      "created_at": "2026-03-25T20:09:34.357931+00:00",
      "due_at": "2026-03-25T20:09:34.357931+00:00",
      "interval_days": 0,
      "ease": 2.3,
      "reps": 0,
      "lapses": 0
    },
    {
      "id": "bulk-1774469374401",
      "de": "angerufen",
      "en": "позвонил",
      "article": "",
      "notes": "",
      "created_at": "2026-03-25T20:09:34.357931+00:00",
      "due_at": "2026-03-25T20:09:34.357931+00:00",
      "interval_days": 0,
      "ease": 2.3,
      "reps": 0,
      "lapses": 0
    },
    {
      "id": "bulk-1774469374402",
      "de": "sonnig",
      "en": "солнечно",
      "article": "",
      "notes": "",
      "created_at": "2026-03-25T20:09:34.357931+00:00",
      "due_at": "2026-03-25T20:09:34.357931+00:00",
      "interval_days": 0,
      "ease": 2.3,
      "reps": 0,
      "lapses": 0
    },
    {
      "id": "bulk-1774469374403",
      "de": "windig",
      "en": "ветрено",
      "article": "",
      "notes": "",
      "created_at": "2026-03-25T20:09:34.357931+00:00",
      "due_at": "2026-03-25T20:09:34.357931+00:00",
      "interval_days": 0,
      "ease": 2.3,
      "reps": 0,
      "lapses": 0
    },
    {
      "id": "bulk-1774469374404",
      "de": "bewölkt",
      "en": "облачно",
      "article": "",
      "notes": "",
      "created_at": "2026-03-25T20:09:34.357931+00:00",
      "due_at": "2026-03-25T20:09:34.357931+00:00",
      "interval_days": 0,
      "ease": 2.3,
      "reps": 0,
      "lapses": 0
    },
    {
      "id": "bulk-1774469374405",
      "de": "es regnet",
      "en": "идёт дождь",
      "article": "",
      "notes": "",
      "created_at": "2026-03-25T20:09:34.357931+00:00",
      "due_at": "2026-03-25T20:09:34.357931+00:00",
      "interval_days": 0,
      "ease": 2.3,
      "reps": 0,
      "lapses": 0
    },
    {
      "id": "bulk-1774469374406",
      "de": "es schneit",
      "en": "идёт снег",
      "article": "",
      "notes": "",
      "created_at": "2026-03-25T20:09:34.357931+00:00",
      "due_at": "2026-03-25T20:09:34.357931+00:00",
      "interval_days": 0,
      "ease": 2.3,
      "reps": 0,
      "lapses": 0
    },
    {
      "id": "bulk-1774469374407",
      "de": "dabei",
      "en": "при этом / с собой",
      "article": "",
      "notes": "",
      "created_at": "2026-03-25T20:09:34.357931+00:00",
      "due_at": "2026-03-25T20:09:34.357931+00:00",
      "interval_days": 0,
      "ease": 2.3,
      "reps": 0,
      "lapses": 0
    }
  ]
}